<annotation>
	<folder>image and xml</folder>
	<filename>X51006619343.jpg</filename>
	<path>/home/miracle/Downloads/task1_sangeeta_KT/image and xml/X51006619343.jpg</path>
	<source>
		<database>Unknown</database>
	</source>
	<size>
		<width>888</width>
		<height>2185</height>
		<depth>1</depth>
	</size>
	<segmented>0</segmented>
	<object>
		<name>Total</name>
		<pose>Unspecified</pose>
		<truncated>0</truncated>
		<difficult>0</difficult>
		<bndbox>
			<xmin>70</xmin>
			<ymin>1435</ymin>
			<xmax>843</xmax>
			<ymax>1496</ymax>
		</bndbox>
	</object>
	<object>
		<name>Date</name>
		<pose>Unspecified</pose>
		<truncated>0</truncated>
		<difficult>0</difficult>
		<bndbox>
			<xmin>68</xmin>
			<ymin>1732</ymin>
			<xmax>240</xmax>
			<ymax>1801</ymax>
		</bndbox>
	</object>
</annotation>
