<annotation>
	<folder>train1</folder>
	<filename>X51005361950.jpg</filename>
	<path>/home/miracle/Downloads/train1/X51005361950.jpg</path>
	<source>
		<database>Unknown</database>
	</source>
	<size>
		<width>949</width>
		<height>1349</height>
		<depth>3</depth>
	</size>
	<segmented>0</segmented>
	<object>
		<name>Total</name>
		<pose>Unspecified</pose>
		<truncated>0</truncated>
		<difficult>0</difficult>
		<bndbox>
			<xmin>82</xmin>
			<ymin>823</ymin>
			<xmax>848</xmax>
			<ymax>903</ymax>
		</bndbox>
	</object>
	<object>
		<name>Date</name>
		<pose>Unspecified</pose>
		<truncated>0</truncated>
		<difficult>0</difficult>
		<bndbox>
			<xmin>655</xmin>
			<ymin>590</ymin>
			<xmax>823</xmax>
			<ymax>658</ymax>
		</bndbox>
	</object>
</annotation>
