<annotation>
	<folder>train1</folder>
	<filename>X51005745188.jpg</filename>
	<path>/home/miracle/Downloads/train1/X51005745188.jpg</path>
	<source>
		<database>Unknown</database>
	</source>
	<size>
		<width>706</width>
		<height>1659</height>
		<depth>1</depth>
	</size>
	<segmented>0</segmented>
	<object>
		<name>Total</name>
		<pose>Unspecified</pose>
		<truncated>0</truncated>
		<difficult>0</difficult>
		<bndbox>
			<xmin>71</xmin>
			<ymin>1012</ymin>
			<xmax>680</xmax>
			<ymax>1057</ymax>
		</bndbox>
	</object>
	<object>
		<name>Date</name>
		<pose>Unspecified</pose>
		<truncated>0</truncated>
		<difficult>0</difficult>
		<bndbox>
			<xmin>467</xmin>
			<ymin>535</ymin>
			<xmax>637</xmax>
			<ymax>576</ymax>
		</bndbox>
	</object>
</annotation>
